pcapng_utils/__init__.py
pcapng_utils/payload.py
pcapng_utils/pcapng_to_har.py
pcapng_utils/har/__init__.py
pcapng_utils/har/pirogue_enrichment/__init__.py
pcapng_utils/har/pirogue_enrichment/base.py
pcapng_utils/har/pirogue_enrichment/decryption.py
pcapng_utils/har/pirogue_enrichment/sorted_list.py
pcapng_utils/har/pirogue_enrichment/stacktrace.py
pcapng_utils/har/pirogue_enrichment/types.py
pcapng_utils/har/pirogue_enrichment/utils.py
pcapng_utils/tshark/__init__.py
pcapng_utils/tshark/traffic.py
pcapng_utils/tshark/types.py
pcapng_utils/tshark/utils.py
pcapng_utils/tshark/wrapper.py
pcapng_utils/tshark/protocols/__init__.py
pcapng_utils/tshark/protocols/http1.py
pcapng_utils/tshark/protocols/http2.py
pcapng_utils-1.0.10.dist-info/licenses/LICENSE
pcapng_utils-1.0.10.dist-info/METADATA
pcapng_utils-1.0.10.dist-info/WHEEL
pcapng_utils-1.0.10.dist-info/entry_points.txt
pcapng_utils-1.0.10.dist-info/top_level.txt
pcapng_utils-1.0.10.dist-info/RECORD
