Metadata-Version: 2.4
Name: pcapng-utils
Version: 1.0.10
Summary: A set of Python scripts to manipulate PCAPNG files
Author-email: "Étienne Maheux (PEReN)" <etienne.maheux@peren.gouv.fr>, "Esther Onfroy (PEReN)" <esther.onfroy@peren.gouv.fr>
Maintainer-email: U+039b <hello@pts-project.org>
License: GPL-3.0+ AND MIT
Project-URL: repository, https://github.com/PiRogueToolSuite/pcapng-utils
Project-URL: issues, https://github.com/PiRogueToolSuite/pcapng-utils/issues
Requires-Python: >=3.11
License-File: LICENSE
Requires-Dist: communityid==1.5.0
Requires-Dist: sortedcontainers==2.4.0
Requires-Dist: tyro==0.*
Dynamic: license-file
